rightnow_cli/__init__.py
rightnow_cli/__main__.py
rightnow_cli/bench.py
rightnow_cli/cache.py
rightnow_cli/chat_agent.py
rightnow_cli/cli_minimal.py
rightnow_cli/compiler.py
rightnow_cli/correctness.py
rightnow_cli/exceptions.py
rightnow_cli/interactive.py
rightnow_cli/kernel_analyzer.py
rightnow_cli/logger.py
rightnow_cli/openrouter.py
rightnow_cli/openrouter_v2.py
rightnow_cli/profiler.py
rightnow_cli/agents/__init__.py
rightnow_cli/agents/analyzer_agent.py
rightnow_cli/agents/base_agent.py
rightnow_cli/agents/cuda_agent.py
rightnow_cli/agents/debugger_agent.py
rightnow_cli/agents/enhanced_base_agent.py
rightnow_cli/agents/general_agent.py
rightnow_cli/agents/optimizer_agent.py
rightnow_cli/agents/orchestrator.py
rightnow_cli/ai/__init__.py
rightnow_cli/ai/async_client.py
rightnow_cli/backends/__init__.py
rightnow_cli/backends/base.py
rightnow_cli/backends/cuda_backend.py
rightnow_cli/config/__init__.py
rightnow_cli/config/manager.py
rightnow_cli/config/schema.py
rightnow_cli/config/templates.py
rightnow_cli/config/utils.py
rightnow_cli/core/__init__.py
rightnow_cli/core/async_optimizer.py
rightnow_cli/kernels/__init__.py
rightnow_cli/kernels/base.py
rightnow_cli/permissions/__init__.py
rightnow_cli/permissions/checker.py
rightnow_cli/permissions/manager.py
rightnow_cli/permissions/matcher.py
rightnow_cli/permissions/prompter.py
rightnow_cli/plugins/__init__.py
rightnow_cli/plugins/manager.py
rightnow_cli/sessions/__init__.py
rightnow_cli/sessions/exporter.py
rightnow_cli/sessions/manager.py
rightnow_cli/sessions/models.py
rightnow_cli/sessions/storage.py
rightnow_cli/tools/__init__.py
rightnow_cli/tools/analyze_cuda.py
rightnow_cli/tools/base.py
rightnow_cli/tools/bash_exec.py
rightnow_cli/tools/benchmark_cuda.py
rightnow_cli/tools/compile_cuda.py
rightnow_cli/tools/gpu_status.py
rightnow_cli/tools/list_files.py
rightnow_cli/tools/profile_cuda.py
rightnow_cli/tools/read_file.py
rightnow_cli/tools/registry.py
rightnow_cli/tools/write_file.py
rightnow_cli-1.0.0.dist-info/licenses/LICENSE
rightnow_cli-1.0.0.dist-info/METADATA
rightnow_cli-1.0.0.dist-info/WHEEL
rightnow_cli-1.0.0.dist-info/entry_points.txt
rightnow_cli-1.0.0.dist-info/top_level.txt
rightnow_cli-1.0.0.dist-info/RECORD
