Metadata-Version: 2.4
Name: rightnow-cli
Version: 1.0.0
Summary: RightNow CLI - GPU-Native AI Code Editor for CUDA development
Author-email: RightNow AI Team <jaber@rightnowai.co>
License: Proprietary
Project-URL: Homepage, https://rightnowai.co
Project-URL: Bug Tracker, https://github.com/RightNow-AI/rightnow-cli/issues
Project-URL: Documentation, https://docs.rightnowai.co/cli
Keywords: gpu,cuda,optimization,kernel,ai,performance,rightnow,code-editor,nvidia,assistant
Classifier: Development Status :: 4 - Beta
Classifier: Intended Audience :: Developers
Classifier: Intended Audience :: Science/Research
Classifier: License :: Other/Proprietary License
Classifier: Programming Language :: Python :: 3
Classifier: Programming Language :: Python :: 3.9
Classifier: Programming Language :: Python :: 3.10
Classifier: Programming Language :: Python :: 3.11
Classifier: Programming Language :: Python :: 3.12
Classifier: Topic :: Software Development :: Code Generators
Classifier: Topic :: Scientific/Engineering :: Artificial Intelligence
Classifier: Topic :: System :: Hardware :: Symmetric Multi-processing
Requires-Python: >=3.9
License-File: LICENSE
Requires-Dist: requests>=2.31.0
Requires-Dist: rich>=13.5.0
Requires-Dist: prompt-toolkit>=3.0.0
Requires-Dist: pygments>=2.15.0
Provides-Extra: dev
Requires-Dist: pytest>=7.4.0; extra == "dev"
Requires-Dist: pytest-mock>=3.11.0; extra == "dev"
Requires-Dist: black>=23.0.0; extra == "dev"
Requires-Dist: isort>=5.12.0; extra == "dev"
Requires-Dist: mypy>=1.0.0; extra == "dev"
Dynamic: license-file
